TinyEarn/TinyEarn.py
TinyEarn/__init__.py
TinyEarn-0.0.13.dist-info/METADATA
TinyEarn-0.0.13.dist-info/WHEEL
TinyEarn-0.0.13.dist-info/top_level.txt
TinyEarn-0.0.13.dist-info/RECORD
