Metadata-Version: 2.1
Name: TinyEarn
Version: 0.0.13
Summary: Simple selenium webscaper to pull earnings data from zacks.com
Home-page: https://github.com/hussien-hussien/TinyEarn
Author: Hussien Hussien
Author-email: me@hussien.net
License: UNKNOWN
Keywords: pandas,earnings report,earnings per share,revenue,finance,zacks.com,investment
Platform: any
Classifier: Programming Language :: Python :: 3
Classifier: License :: OSI Approved :: MIT License
Classifier: Operating System :: OS Independent
Requires-Python: >=3.6
Requires-Dist: pandas (>=0.25.3)
Requires-Dist: numpy (>=1.15.4)
Requires-Dist: selenium (>=3.3.0requests>=2.23)
Requires-Dist: beautifulsoup4 (>=4.9.0)
Requires-Dist: geckodriver-autoinstaller (>=0.1)
